blockcrawler/__init__.py
blockcrawler/__main__.py
blockcrawler/core/__init__.py
blockcrawler/core/bus.py
blockcrawler/core/click.py
blockcrawler/core/entities.py
blockcrawler/core/rpc.py
blockcrawler/core/stats.py
blockcrawler/core/types.py
blockcrawler/evm/__init__.py
blockcrawler/evm/bin.py
blockcrawler/evm/data_packages.py
blockcrawler/evm/producers.py
blockcrawler/evm/rpc.py
blockcrawler/evm/services.py
blockcrawler/evm/transformers.py
blockcrawler/evm/types.py
blockcrawler/evm/util.py
blockcrawler/nft/__init__.py
blockcrawler/nft/consumers.py
blockcrawler/nft/data_packages.py
blockcrawler/nft/entities.py
blockcrawler/nft/bin/__init__.py
blockcrawler/nft/bin/crawl.py
blockcrawler/nft/bin/force.py
blockcrawler/nft/bin/load.py
blockcrawler/nft/bin/nft.py
blockcrawler/nft/bin/reset.py
blockcrawler/nft/bin/seed.py
blockcrawler/nft/bin/shared.py
blockcrawler/nft/bin/tail.py
blockcrawler/nft/bin/verify.py
blockcrawler/nft/data/__init__.py
blockcrawler/nft/data/models.py
blockcrawler/nft/data_services/__init__.py
blockcrawler/nft/data_services/dynamodb.py
blockcrawler/nft/evm/__init__.py
blockcrawler/nft/evm/consumers.py
blockcrawler/nft/evm/oracles.py
blockcrawler/nft/evm/transformers.py
block_crawler-1.2.3.dist-info/LICENSE
block_crawler-1.2.3.dist-info/METADATA
block_crawler-1.2.3.dist-info/WHEEL
block_crawler-1.2.3.dist-info/entry_points.txt
block_crawler-1.2.3.dist-info/top_level.txt
block_crawler-1.2.3.dist-info/RECORD
