Metadata-Version: 2.1
Name: block-crawler
Version: 1.2.3
Summary: Crawls blocks from a blockchain node, parses the blocks for data, and populates the NFT database
Author-email: "Adam L. Englander" <adam@zetta.fi>
License: Mozilla Public License Version 2.0
Project-URL: Chat, https://github.com/block-crawler/block-crawler/discussions
Project-URL: Documentation, https://block-crawler.readthedocs.io
Project-URL: Changes, https://github.com/block-crawler/block-crawler/blob/main/CHANGES.md
Project-URL: Source Code, https://github.com/block-crawler/block-crawler
Project-URL: Issue Tracker, https://github.com/block-crawler/block-crawler/issues/
Classifier: Programming Language :: Python :: 3
Classifier: Development Status :: 5 - Production/Stable
Classifier: Environment :: Console
Classifier: Framework :: AsyncIO
Classifier: Intended Audience :: Information Technology
Classifier: License :: OSI Approved :: Mozilla Public License 2.0 (MPL 2.0)
Classifier: Operating System :: OS Independent
Classifier: Topic :: Software Development :: Libraries :: Application Frameworks
Classifier: Topic :: Utilities
Classifier: Typing :: Typed
Requires-Python: <3.11,>=3.8
License-File: LICENSE
Requires-Dist: aioboto3 (~=9.6)
Requires-Dist: botocore (~=1.24)
Requires-Dist: aiohttp (~=3.8)
Requires-Dist: aiodns (~=3.0)
Requires-Dist: requests (~=2.28)
Requires-Dist: click (~=8.1)
Requires-Dist: colorama (~=0.4)
Requires-Dist: pycryptodome (~=3.15)
Requires-Dist: eth-abi (~=3.0)
Requires-Dist: eth-bloom (~=1.0)
Requires-Dist: hexbytes (~=0.3)
Requires-Dist: backoff (~=2.2)
Requires-Dist: psutil (~=5.9)
Provides-Extra: build
Requires-Dist: build (~=0.10) ; extra == 'build'
Requires-Dist: twine (~=4.0) ; extra == 'build'
Provides-Extra: dev
Requires-Dist: pre-commit (~=3.0) ; extra == 'dev'
Requires-Dist: tox (~=4.4) ; extra == 'dev'
Requires-Dist: black (~=22.6) ; extra == 'dev'
Requires-Dist: flake8 (~=4.0) ; extra == 'dev'
Requires-Dist: flake8-gl-codeclimate (~=0.1) ; extra == 'dev'
Requires-Dist: mypy (~=0.971) ; extra == 'dev'
Requires-Dist: types-aioboto3 (~=9.6) ; extra == 'dev'
Requires-Dist: types-psutil (~=5.9) ; extra == 'dev'
Requires-Dist: ddt (~=1.5) ; extra == 'dev'
Requires-Dist: coverage[toml] (~=6.4) ; extra == 'dev'
Requires-Dist: unittest-xml-reporting (~=3.2) ; extra == 'dev'
Requires-Dist: python-dotenv (~=0.20) ; extra == 'dev'
Provides-Extra: docs
Requires-Dist: sphinx (~=5.3) ; extra == 'docs'
Requires-Dist: pydata-sphinx-theme (~=0.12) ; extra == 'docs'
Requires-Dist: sphinx-design (~=0.3) ; extra == 'docs'
